object_serializer-0.0.1.dist-info/DESCRIPTION.rst
object_serializer-0.0.1.dist-info/METADATA
object_serializer-0.0.1.dist-info/RECORD
object_serializer-0.0.1.dist-info/WHEEL
object_serializer-0.0.1.dist-info/metadata.json
object_serializer-0.0.1.dist-info/top_level.txt
serializer/__init__.py
serializer/association.py
serializer/attribute.py
serializer/serializer.py
